schemaorg_types/AMRadioChannel.py
schemaorg_types/APIReference.py
schemaorg_types/Abdomen.py
schemaorg_types/AboutPage.py
schemaorg_types/AcceptAction.py
schemaorg_types/Accommodation.py
schemaorg_types/AccountingService.py
schemaorg_types/AchieveAction.py
schemaorg_types/Action.py
schemaorg_types/ActionAccessSpecification.py
schemaorg_types/ActionStatusType.py
schemaorg_types/ActivateAction.py
schemaorg_types/ActivationFee.py
schemaorg_types/ActiveActionStatus.py
schemaorg_types/ActiveNotRecruiting.py
schemaorg_types/AddAction.py
schemaorg_types/AdministrativeArea.py
schemaorg_types/AdultEntertainment.py
schemaorg_types/AdultOrientedEnumeration.py
schemaorg_types/AdvertiserContentArticle.py
schemaorg_types/AerobicActivity.py
schemaorg_types/AggregateOffer.py
schemaorg_types/AggregateRating.py
schemaorg_types/AgreeAction.py
schemaorg_types/Airline.py
schemaorg_types/Airport.py
schemaorg_types/AlbumRelease.py
schemaorg_types/AlcoholConsideration.py
schemaorg_types/AlignmentObject.py
schemaorg_types/AllWheelDriveConfiguration.py
schemaorg_types/AllergiesHealthAspect.py
schemaorg_types/AllocateAction.py
schemaorg_types/AmpStory.py
schemaorg_types/AmusementPark.py
schemaorg_types/AnaerobicActivity.py
schemaorg_types/AnalysisNewsArticle.py
schemaorg_types/AnatomicalStructure.py
schemaorg_types/AnatomicalSystem.py
schemaorg_types/AndroidPlatform.py
schemaorg_types/Anesthesia.py
schemaorg_types/AnimalShelter.py
schemaorg_types/Answer.py
schemaorg_types/Apartment.py
schemaorg_types/ApartmentComplex.py
schemaorg_types/Appearance.py
schemaorg_types/AppendAction.py
schemaorg_types/ApplyAction.py
schemaorg_types/ApprovedIndication.py
schemaorg_types/Aquarium.py
schemaorg_types/ArchiveComponent.py
schemaorg_types/ArchiveOrganization.py
schemaorg_types/ArriveAction.py
schemaorg_types/ArtGallery.py
schemaorg_types/Artery.py
schemaorg_types/Article.py
schemaorg_types/AskAction.py
schemaorg_types/AskPublicNewsArticle.py
schemaorg_types/AssessAction.py
schemaorg_types-0.4.0.dist-info/LICENSE
schemaorg_types-0.4.0.dist-info/WHEEL
schemaorg_types-0.4.0.dist-info/METADATA
schemaorg_types-0.4.0.dist-info/RECORD
